atla_mcp_server/__init__.py
atla_mcp_server/__main__.py
atla_mcp_server/debug.py
atla_mcp_server/server.py
atla_mcp_server-0.1.2.dist-info/METADATA
atla_mcp_server-0.1.2.dist-info/WHEEL
atla_mcp_server-0.1.2.dist-info/entry_points.txt
atla_mcp_server-0.1.2.dist-info/licenses/LICENSE
atla_mcp_server-0.1.2.dist-info/RECORD
