Metadata-Version: 2.4
Name: atla-mcp-server
Version: 0.1.2
Summary: An MCP server implementation providing a standardized interface for LLMs to interact with the Atla API.
Project-URL: Homepage, https://atla-ai.com
Project-URL: Repository, https://github.com/atla-ai/atla-mcp-server
Project-URL: Issues, https://github.com/atla-ai/atla-mcp-server/issues
Author-email: Atla <team@atla-ai.com>
License: MIT
License-File: LICENSE
Classifier: Development Status :: 4 - Beta
Classifier: Intended Audience :: Developers
Classifier: License :: OSI Approved :: MIT License
Classifier: Programming Language :: Python :: 3
Classifier: Programming Language :: Python :: 3.11
Requires-Python: >=3.11
Requires-Dist: atla>=0.6.0
Requires-Dist: mcp[cli]>=1.6.0
Provides-Extra: dev
Requires-Dist: mypy>=1.15.0; extra == 'dev'
Requires-Dist: pre-commit>=3.7.1; extra == 'dev'
Requires-Dist: ruff>=0.9.7; extra == 'dev'
